telegram_types/__init__.py
telegram_types/base.py
telegram_types/enums/__init__.py
telegram_types/enums/auto_name.py
telegram_types/enums/chat_event_action.py
telegram_types/enums/chat_member_status.py
telegram_types/enums/chat_type.py
telegram_types/enums/message_media_type.py
telegram_types/enums/message_service_type.py
telegram_types/enums/parse_mode.py
telegram_types/enums/poll_type.py
telegram_types/enums/user_status.py
telegram_types/functions/__init__.py
telegram_types/functions/generate_file_name.py
telegram_types/media_attributes.py
telegram_types/types/__init__.py
telegram_types/types/callback_query.py
telegram_types/types/chat.py
telegram_types/types/chat_photo.py
telegram_types/types/deleted_messages.py
telegram_types/types/input_file.py
telegram_types/types/keyboard.py
telegram_types/types/media/__init__.py
telegram_types/types/media/animation.py
telegram_types/types/media/audio.py
telegram_types/types/media/base_media.py
telegram_types/types/media/contact.py
telegram_types/types/media/dice.py
telegram_types/types/media/document.py
telegram_types/types/media/game.py
telegram_types/types/media/location.py
telegram_types/types/media/photo.py
telegram_types/types/media/poll.py
telegram_types/types/media/reaction.py
telegram_types/types/media/sticker.py
telegram_types/types/media/thumbnail.py
telegram_types/types/media/venue.py
telegram_types/types/media/video.py
telegram_types/types/media/video_note.py
telegram_types/types/media/voice.py
telegram_types/types/media/webpage.py
telegram_types/types/message.py
telegram_types/types/restriction.py
telegram_types/types/user.py
telegram_types/utils.py
telegram_types-1.49.dist-info/METADATA
telegram_types-1.49.dist-info/WHEEL
telegram_types-1.49.dist-info/RECORD
