Metadata-Version: 2.4
Name: telegram-types
Version: 1.49
Summary: 
Author: Dan
Requires-Python: >=3.8,<4.0
Classifier: Programming Language :: Python :: 3
Classifier: Programming Language :: Python :: 3.8
Classifier: Programming Language :: Python :: 3.9
Classifier: Programming Language :: Python :: 3.10
Classifier: Programming Language :: Python :: 3.11
Classifier: Programming Language :: Python :: 3.12
Classifier: Programming Language :: Python :: 3.13
Classifier: Programming Language :: Python :: 3.14
Requires-Dist: annotated-types (==0.6.0)
Requires-Dist: pydantic (==2.6.4)
Requires-Dist: typing_extensions (==4.10.0)
